{"nodes": [{"id": "c_users_administrator_desktop_\u0645\u0646\u0638\u0648\u0645\u0629_\u0643\u0641\u064a\u0644_test_financialengine_test_ts", "label": "financialEngine.test.ts", "file_type": "code", "source_file": "C:\\Users\\Administrator\\Desktop\\\u0645\u0646\u0638\u0648\u0645\u0629 \u0643\u0641\u064a\u0644\\test\\financialEngine.test.ts", "source_location": "L1"}, {"id": "test_financialengine_test_result", "label": "result", "file_type": "code", "source_file": "C:\\Users\\Administrator\\Desktop\\\u0645\u0646\u0638\u0648\u0645\u0629 \u0643\u0641\u064a\u0644\\test\\financialEngine.test.ts", "source_location": "L25"}, {"id": "test_financialengine_test_base", "label": "base", "file_type": "code", "source_file": "C:\\Users\\Administrator\\Desktop\\\u0645\u0646\u0638\u0648\u0645\u0629 \u0643\u0641\u064a\u0644\\test\\financialEngine.test.ts", "source_location": "L95"}, {"id": "test_financialengine_test_lowsalary", "label": "lowSalary", "file_type": "code", "source_file": "C:\\Users\\Administrator\\Desktop\\\u0645\u0646\u0638\u0648\u0645\u0629 \u0643\u0641\u064a\u0644\\test\\financialEngine.test.ts", "source_location": "L116"}], "edges": [{"source": "c_users_administrator_desktop_\u0645\u0646\u0638\u0648\u0645\u0629_\u0643\u0641\u064a\u0644_test_financialengine_test_ts", "target": "vitest", "relation": "imports_from", "context": "import", "confidence": "EXTRACTED", "source_file": "C:\\Users\\Administrator\\Desktop\\\u0645\u0646\u0638\u0648\u0645\u0629 \u0643\u0641\u064a\u0644\\test\\financialEngine.test.ts", "source_location": "L1", "weight": 1.0}, {"source": "c_users_administrator_desktop_\u0645\u0646\u0638\u0648\u0645\u0629_\u0643\u0641\u064a\u0644_test_financialengine_test_ts", "target": "c_users_administrator_desktop_\u0645\u0646\u0638\u0648\u0645\u0629_\u0643\u0641\u064a\u0644_src_lib_financialengine_ts", "relation": "imports_from", "context": "import", "confidence": "EXTRACTED", "source_file": "C:\\Users\\Administrator\\Desktop\\\u0645\u0646\u0638\u0648\u0645\u0629 \u0643\u0641\u064a\u0644\\test\\financialEngine.test.ts", "source_location": "L2", "weight": 1.0}, {"source": "c_users_administrator_desktop_\u0645\u0646\u0638\u0648\u0645\u0629_\u0643\u0641\u064a\u0644_test_financialengine_test_ts", "target": "lib_financialengine_calculatemurabaha", "relation": "imports", "context": "import", "confidence": "EXTRACTED", "source_file": "C:\\Users\\Administrator\\Desktop\\\u0645\u0646\u0638\u0648\u0645\u0629 \u0643\u0641\u064a\u0644\\test\\financialEngine.test.ts", "source_location": "L2", "weight": 1.0}, {"source": "c_users_administrator_desktop_\u0645\u0646\u0638\u0648\u0645\u0629_\u0643\u0641\u064a\u0644_test_financialengine_test_ts", "target": "lib_financialengine_term_months", "relation": "imports", "context": "import", "confidence": "EXTRACTED", "source_file": "C:\\Users\\Administrator\\Desktop\\\u0645\u0646\u0638\u0648\u0645\u0629 \u0643\u0641\u064a\u0644\\test\\financialEngine.test.ts", "source_location": "L2", "weight": 1.0}, {"source": "c_users_administrator_desktop_\u0645\u0646\u0638\u0648\u0645\u0629_\u0643\u0641\u064a\u0644_test_financialengine_test_ts", "target": "lib_financialengine_calcinput", "relation": "imports", "context": "import", "confidence": "EXTRACTED", "source_file": "C:\\Users\\Administrator\\Desktop\\\u0645\u0646\u0638\u0648\u0645\u0629 \u0643\u0641\u064a\u0644\\test\\financialEngine.test.ts", "source_location": "L2", "weight": 1.0}, {"source": "c_users_administrator_desktop_\u0645\u0646\u0638\u0648\u0645\u0629_\u0643\u0641\u064a\u0644_test_financialengine_test_ts", "target": "test_financialengine_test_result", "relation": "contains", "confidence": "EXTRACTED", "source_file": "C:\\Users\\Administrator\\Desktop\\\u0645\u0646\u0638\u0648\u0645\u0629 \u0643\u0641\u064a\u0644\\test\\financialEngine.test.ts", "source_location": "L25", "weight": 1.0}, {"source": "c_users_administrator_desktop_\u0645\u0646\u0638\u0648\u0645\u0629_\u0643\u0641\u064a\u0644_test_financialengine_test_ts", "target": "test_financialengine_test_result", "relation": "contains", "confidence": "EXTRACTED", "source_file": "C:\\Users\\Administrator\\Desktop\\\u0645\u0646\u0638\u0648\u0645\u0629 \u0643\u0641\u064a\u0644\\test\\financialEngine.test.ts", "source_location": "L31", "weight": 1.0}, {"source": "c_users_administrator_desktop_\u0645\u0646\u0638\u0648\u0645\u0629_\u0643\u0641\u064a\u0644_test_financialengine_test_ts", "target": "test_financialengine_test_result", "relation": "contains", "confidence": "EXTRACTED", "source_file": "C:\\Users\\Administrator\\Desktop\\\u0645\u0646\u0638\u0648\u0645\u0629 \u0643\u0641\u064a\u0644\\test\\financialEngine.test.ts", "source_location": "L40", "weight": 1.0}, {"source": "c_users_administrator_desktop_\u0645\u0646\u0638\u0648\u0645\u0629_\u0643\u0641\u064a\u0644_test_financialengine_test_ts", "target": "test_financialengine_test_result", "relation": "contains", "confidence": "EXTRACTED", "source_file": "C:\\Users\\Administrator\\Desktop\\\u0645\u0646\u0638\u0648\u0645\u0629 \u0643\u0641\u064a\u0644\\test\\financialEngine.test.ts", "source_location": "L51", "weight": 1.0}, {"source": "c_users_administrator_desktop_\u0645\u0646\u0638\u0648\u0645\u0629_\u0643\u0641\u064a\u0644_test_financialengine_test_ts", "target": "test_financialengine_test_result", "relation": "contains", "confidence": "EXTRACTED", "source_file": "C:\\Users\\Administrator\\Desktop\\\u0645\u0646\u0638\u0648\u0645\u0629 \u0643\u0641\u064a\u0644\\test\\financialEngine.test.ts", "source_location": "L58", "weight": 1.0}, {"source": "c_users_administrator_desktop_\u0645\u0646\u0638\u0648\u0645\u0629_\u0643\u0641\u064a\u0644_test_financialengine_test_ts", "target": "test_financialengine_test_result", "relation": "contains", "confidence": "EXTRACTED", "source_file": "C:\\Users\\Administrator\\Desktop\\\u0645\u0646\u0638\u0648\u0645\u0629 \u0643\u0641\u064a\u0644\\test\\financialEngine.test.ts", "source_location": "L68", "weight": 1.0}, {"source": "c_users_administrator_desktop_\u0645\u0646\u0638\u0648\u0645\u0629_\u0643\u0641\u064a\u0644_test_financialengine_test_ts", "target": "test_financialengine_test_result", "relation": "contains", "confidence": "EXTRACTED", "source_file": "C:\\Users\\Administrator\\Desktop\\\u0645\u0646\u0638\u0648\u0645\u0629 \u0643\u0641\u064a\u0644\\test\\financialEngine.test.ts", "source_location": "L77", "weight": 1.0}, {"source": "c_users_administrator_desktop_\u0645\u0646\u0638\u0648\u0645\u0629_\u0643\u0641\u064a\u0644_test_financialengine_test_ts", "target": "test_financialengine_test_result", "relation": "contains", "confidence": "EXTRACTED", "source_file": "C:\\Users\\Administrator\\Desktop\\\u0645\u0646\u0638\u0648\u0645\u0629 \u0643\u0641\u064a\u0644\\test\\financialEngine.test.ts", "source_location": "L83", "weight": 1.0}, {"source": "c_users_administrator_desktop_\u0645\u0646\u0638\u0648\u0645\u0629_\u0643\u0641\u064a\u0644_test_financialengine_test_ts", "target": "test_financialengine_test_result", "relation": "contains", "confidence": "EXTRACTED", "source_file": "C:\\Users\\Administrator\\Desktop\\\u0645\u0646\u0638\u0648\u0645\u0629 \u0643\u0641\u064a\u0644\\test\\financialEngine.test.ts", "source_location": "L88", "weight": 1.0}, {"source": "c_users_administrator_desktop_\u0645\u0646\u0638\u0648\u0645\u0629_\u0643\u0641\u064a\u0644_test_financialengine_test_ts", "target": "test_financialengine_test_base", "relation": "contains", "confidence": "EXTRACTED", "source_file": "C:\\Users\\Administrator\\Desktop\\\u0645\u0646\u0638\u0648\u0645\u0629 \u0643\u0641\u064a\u0644\\test\\financialEngine.test.ts", "source_location": "L95", "weight": 1.0}, {"source": "c_users_administrator_desktop_\u0645\u0646\u0638\u0648\u0645\u0629_\u0643\u0641\u064a\u0644_test_financialengine_test_ts", "target": "test_financialengine_test_lowsalary", "relation": "contains", "confidence": "EXTRACTED", "source_file": "C:\\Users\\Administrator\\Desktop\\\u0645\u0646\u0638\u0648\u0645\u0629 \u0643\u0641\u064a\u0644\\test\\financialEngine.test.ts", "source_location": "L116", "weight": 1.0}], "raw_calls": []}